setup.py
pybold/__init__.py
pybold/sequence.py
pybold/specimen.py
pybold/tracefile.py
pybold.egg-info/PKG-INFO
pybold.egg-info/SOURCES.txt
pybold.egg-info/dependency_links.txt
pybold.egg-info/pbr.json
pybold.egg-info/requires.txt
pybold.egg-info/top_level.txt
tests/__init__.py
tests/testsequence.py
tests/testspecimen.py
tests/testtracefile.py