Metadata-Version: 1.1
Name: pybold
Version: 0.1.5
Summary: Barcode of Life Public API consumers in Python 2.7
Home-page: UNKNOWN
Author: Iyad Kandalaft
Author-email: iyad.kandalaft@canada.ca
License: LGPL v3
Platform: UNKNOWN
Classifier: License :: OSI Approved :: GNU Lesser General Public License v3 (LGPLv3)
Classifier: Programming Language :: Python :: 2.7
Classifier: Topic :: Scientific/Engineering :: Bio-Informatics
Classifier: Development Status :: 4 - Beta
